MultiPoint/CORRcalc.py
MultiPoint/FEcalc.py
MultiPoint/GAMcalc.py
MultiPoint/GAMcalc2.py
MultiPoint/GAMcalcRR.py
MultiPoint/MultiPoint.py
MultiPoint/MultiPointTemp.py
MultiPoint/TestWLC.py
MultiPoint/WLCgreen.py
MultiPoint/WLCgreenTemp.py
MultiPoint/__init__.py
MultiPoint/anAttempt.py
MultiPoint/phasediag.py
MultiPoint/propagator.py
MultiPoint/removeExtraWS.py
MultiPoint/rewrite.py
MultiPoint/scatter.py
MultiPoint/special.py
MultiPoint/temp.py
MultiPoint/utils.py
MultiPoint/wignerD.py
MultiPoint-0.0.3.dist-info/METADATA
MultiPoint-0.0.3.dist-info/RECORD
MultiPoint-0.0.3.dist-info/WHEEL
MultiPoint-0.0.3.dist-info/top_level.txt
